ossd.py
ossd-1.0.8.dist-info/LICENSE
ossd-1.0.8.dist-info/METADATA
ossd-1.0.8.dist-info/WHEEL
ossd-1.0.8.dist-info/top_level.txt
ossd-1.0.8.dist-info/RECORD
