Metadata-Version: 2.1
Name: ossd
Version: 1.0.8
Summary: OpenSubtitles Subtitles Downloader
Home-page: https://github.com/vorava/ossd
Author: Vojtech Orava
Author-email: vojtech.orava@gmail.com
License: UNKNOWN
Platform: UNKNOWN
Classifier: Programming Language :: Python :: 3
Classifier: License :: OSI Approved :: MIT License
Classifier: Operating System :: OS Independent
License-File: LICENSE
